{
  "Microsoft 365": [],
  "Teams": [],
  "Copilot": [],
  "Windows": [],
  "Surface": [],
  "Xbox": [],
  "Deals": [],
  "Small Business": [],
  "Support": [],
  "Software": {
    "Windows Apps": [],
    "AI": [],
    "Outlook": [],
    "OneDrive": [],
    "Microsoft Teams": [],
    "OneNote": [],
    "Microsoft Edge": [],
    "Skype": []
  },
  "PCs & Devices": {
    "Computers": [],
    "Shop Xbox": [],
    "Accessories": [],
    "VR & mixed reality": [],
    "Certified Refurbished": [],
    "Trade-in for cash": []
  },
  "Entertainment": {
    "Xbox Game Pass Ultimate": [],
    "PC Game Pass": [],
    "Xbox games": [],
    "PC and Windows games": [],
    "Movies & TV": []
  },
  "Business": {
    "Microsoft Cloud": [],
    "Microsoft Security": [],
    "Dynamics 365": [],
    "Microsoft 365 for business": [],
    "Microsoft Power Platform": [],
    "Windows 365": [],
    "Microsoft Industry": [],
    "Small Business": []
  },
  "Developer & IT": {
    "Azure": [],
    "Developer Center": [],
    "Documentation": [],
    "Microsoft Learn": [],
    "Microsoft Tech Community": [],
    "Azure Marketplace": [],
    "AppSource": [],
    "Visual Studio": []
  },
  "Other": {
    "Microsoft Rewards": [],
    "Free downloads & security": [],
    "Education": [],
    "Gift cards": [],
    "Licensing": [],
    "Unlocked stories": []
  },
  "New Products": {
    "Surface Pro": [],
    "Surface Laptop": [],
    "Surface Laptop Studio 2": [],
    "Surface Laptop Go 3": [],
    "Microsoft Copilot": [],
    "AI in Windows": [],
    "Explore Microsoft products": [],
    "Windows 11 apps": []
  },
  "Microsoft Store": {
    "Account profile": [],
    "Download Center": [],
    "Microsoft Store support": [],
    "Returns": [],
    "Order tracking": [],
    "Certified Refurbished": [],
    "Microsoft Store Promise": [],
    "Flexible Payments": []
  },
  "Education": {
    "Microsoft in education": [],
    "Devices for education": [],
    "Microsoft Teams for Education": [],
    "Microsoft 365 Education": [],
    "How to buy for your school": [],
    "Educator training and development": [],
    "Deals for students and parents": [],
    "Azure for students": []
  },
  "Business": {
    "Microsoft Cloud": [],
    "Microsoft Security": [],
    "Dynamics 365": [],
    "Microsoft 365": [],
    "Microsoft Power Platform": [],
    "Microsoft Teams": [],
    "Copilot for Microsoft 365": [],
    "Small Business": []
  },
  "Developer & IT": {
    "Azure": [],
    "Developer Center": [],
    "Documentation": [],
    "Microsoft Learn": [],
    "Microsoft Tech Community": [],
    "Azure Marketplace": [],
    "AppSource": [],
    "Visual Studio": []
  },
  "Company": {
    "Careers": [],
    "About Microsoft": [],
    "Company news": [],
    "Privacy at Microsoft": [],
    "Investors": [],
    "Diversity and inclusion": [],
    "Accessibility": [],
    "Sustainability": []
  },
  "Legal": {
    "Sitemap": [],
    "Contact Microsoft": [],
    "Privacy": [],
    "Manage cookies": [],
    "Terms of use": [],
    "Trademarks": [],
    "Safety & eco": [],
    "Recycling": [],
    "About our ads": [],
    "© Microsoft 2024": []
  }
}